udls/__init__.py
udls/audio_example.py
udls/audio_example_dataset.py
udls/base_dataset.py
udls/duration.py
udls/resample.py
udls/serve.py
udls/simple_dataset.py
udls/transforms.py
udls/generated/__init__.py
udls/generated/audio_example_pb2.py
udls-1.1.4.dist-info/LICENSE
udls-1.1.4.dist-info/METADATA
udls-1.1.4.dist-info/WHEEL
udls-1.1.4.dist-info/entry_points.txt
udls-1.1.4.dist-info/top_level.txt
udls-1.1.4.dist-info/RECORD
