Metadata-Version: 2.1
Name: udls
Version: 1.1.4
Summary: Base class and presets for fast dataset creation inside IRCAM
Author: Antoine CAILLON
Author-email: caillon@ircam.fr
Classifier: Programming Language :: Python :: 3
Classifier: License :: OSI Approved :: MIT License
Classifier: Operating System :: OS Independent
Requires-Python: >=3.7
License-File: LICENSE
